cdk_ecr_image_scan_notify/__init__.py
cdk_ecr_image_scan_notify/py.typed
cdk_ecr_image_scan_notify/_jsii/__init__.py
cdk_ecr_image_scan_notify/_jsii/cdk-ecr-image-scan-notify@1.0.212.jsii.tgz
cdk_ecr_image_scan_notify-1.0.212.dist-info/LICENSE
cdk_ecr_image_scan_notify-1.0.212.dist-info/METADATA
cdk_ecr_image_scan_notify-1.0.212.dist-info/WHEEL
cdk_ecr_image_scan_notify-1.0.212.dist-info/top_level.txt
cdk_ecr_image_scan_notify-1.0.212.dist-info/RECORD
